symbal/__init__.py
symbal/capsule.py
symbal/dataset.py
symbal/ensembles.py
symbal/main.py
symbal/penalties.py
symbal/strategy.py
symbal/test_function.py
symbal/utils.py
symbal-0.0.69.dist-info/LICENSE
symbal-0.0.69.dist-info/METADATA
symbal-0.0.69.dist-info/WHEEL
symbal-0.0.69.dist-info/top_level.txt
symbal-0.0.69.dist-info/RECORD
