Metadata-Version: 2.1
Name: symbal
Version: 0.0.69
Summary: A Python package for batch adaptive sampling with symbolic regression
Home-page: https://github.com/ajsummers/symbal
Author: Alex Summers
Author-email: ajs0201@auburn.edu
License: UNKNOWN
Project-URL: Issues, https://github.com/ajsummers/symbal/issues
Platform: UNKNOWN
Classifier: Programming Language :: Python :: 3
Classifier: License :: OSI Approved :: MIT License
Classifier: Operating System :: OS Independent
Requires-Python: >=3.7
License-File: LICENSE
